apnews/__init__.py
apnews/client.py
apnews-0.1.1.dist-info/LICENSE
apnews-0.1.1.dist-info/METADATA
apnews-0.1.1.dist-info/WHEEL
apnews-0.1.1.dist-info/top_level.txt
apnews-0.1.1.dist-info/RECORD
