Metadata-Version: 2.1
Name: apnews
Version: 0.1.1
Summary: A simple web scraper for Associated Press
Home-page: https://github.com/splch/py-apnews
Author: Spencer Churchill
Author-email: spence@duck.com
Classifier: Development Status :: 3 - Alpha
Classifier: Intended Audience :: Developers
Classifier: License :: OSI Approved :: MIT License
Classifier: Programming Language :: Python :: 3.7
Classifier: Programming Language :: Python :: 3.8
Classifier: Programming Language :: Python :: 3.9
Classifier: Programming Language :: Python :: 3.11
License-File: LICENSE
Requires-Dist: requests
Requires-Dist: beautifulsoup4
